thya/__init__.py
thya/apis.py
thya/dataset.py
thya/summarize.py
Thya-0.0.4.dist-info/LICENSE
Thya-0.0.4.dist-info/METADATA
Thya-0.0.4.dist-info/WHEEL
Thya-0.0.4.dist-info/top_level.txt
Thya-0.0.4.dist-info/RECORD
