Metadata-Version: 2.1
Name: Thya
Version: 0.0.4
Summary: ThyaTechnology SDK
Home-page: https://github.com/ThyaTechnology/thya
Author: Silvio Giancola
Author-email: silvio@thya-technology.com
License: GNU Affero General Public License v3.0
Keywords: Thya,Technology,SDK,Cloud,Computer Vision,Object Detection,Instance Segmentation
Classifier: Development Status :: 3 - Alpha
Classifier: Intended Audience :: Developers
Classifier: Topic :: Software Development :: Build Tools
Classifier: Programming Language :: Python :: 3
Classifier: Programming Language :: Python :: 3.7
Classifier: Programming Language :: Python :: 3.8
Classifier: Programming Language :: Python :: 3.9
Classifier: Programming Language :: Python :: 3.10
Classifier: Programming Language :: Python :: 3.11
License-File: LICENSE
Requires-Dist: requests
Requires-Dist: tqdm
Requires-Dist: xmltodict
Requires-Dist: imagesize
Requires-Dist: xlsxwriter
